tcpchan/__init__.py
tcpchan/aio/__init__.py
tcpchan/aio/proto.py
tcpchan/core/__init__.py
tcpchan/core/chan.py
tcpchan/core/conn.py
tcpchan/core/evt.py
tcpchan/core/msg.py
tcpchan-0.1.1.dist-info/LICENSE
tcpchan-0.1.1.dist-info/WHEEL
tcpchan-0.1.1.dist-info/METADATA
tcpchan-0.1.1.dist-info/RECORD
