Metadata-Version: 2.1
Name: tcpchan
Version: 0.1.1
Summary: tcpchan is a TCP (de)multiplexer
Home-page: https://github.com/frankurcrazy/tcpchan
License: BSD-3-Clause
Keywords: tcp,multiplexer,mux,stream,channel
Author: Frank Chang
Author-email: frank@csie.io
Requires-Python: >=3.7
Classifier: License :: OSI Approved :: BSD License
Classifier: Operating System :: OS Independent
Classifier: Programming Language :: Python :: 3
Classifier: Programming Language :: Python :: 3.7
Classifier: Programming Language :: Python :: 3.8
Classifier: Topic :: Internet
Classifier: Topic :: System :: Networking
Requires-Dist: fpack (>=1.0.0)
Project-URL: Repository, https://github.com/frankurcrazy/tcpchan
